LachoPri/LachoPri.py
LachoPri/__init__.py
LachoPri/utilidadeslacho/Rpy2Odds.py
LachoPri/utilidadeslacho/__init__.py
LachoPri-0.1.dist-info/LICENSE
LachoPri-0.1.dist-info/METADATA
LachoPri-0.1.dist-info/WHEEL
LachoPri-0.1.dist-info/top_level.txt
LachoPri-0.1.dist-info/RECORD
